cobra/__init__.py
cobra/engine/__init__.py
cobra/engine/loader.py
cobra/engine/graphics/__init__.py
cobra/engine/graphics/mesh.py
cobra/engine/graphics/shader.py
cobra/engine/graphics/window.py
cobra/engine/math/__init__.py
cobra/engine/math/matrix.py
cobra/engine/math/vector.py
cobra/engine/scene/__init__.py
cobra/engine/scene/camera.py
cobra/engine/scene/transform.py
cobra_engine-0.1.0.dist-info/LICENSE
cobra_engine-0.1.0.dist-info/METADATA
cobra_engine-0.1.0.dist-info/WHEEL
cobra_engine-0.1.0.dist-info/top_level.txt
cobra_engine-0.1.0.dist-info/RECORD
