Metadata-Version: 2.2
Name: cobra-engine
Version: 0.1.0
Summary: A tiny portable OpenGL framework using PyGame
Author-email: Ron Shani <ronshan4u@gmail.com>
Project-URL: Homepage, https://github.com/The-Cobra-Project/cobra
Project-URL: Issues, https://github.com/The-Cobra-Project/cobra/issues
Classifier: Programming Language :: Python :: 3
Classifier: Operating System :: OS Independent
Classifier: License :: OSI Approved :: MIT License
Classifier: Development Status :: 4 - Beta
Classifier: Environment :: GPU
Classifier: Intended Audience :: Developers
Classifier: Topic :: Games/Entertainment
Requires-Python: >=3.8
License-File: LICENSE
Requires-Dist: numpy
Requires-Dist: pygame
Requires-Dist: PyOpenGL
